{
    "instaloader": {
        "node_type": "Post",
        "version": "4.14.1"
    },
    "node": {
        "__isXDTGraphMediaInterface": "XDTGraphVideo",
        "__typename": "GraphVideo",
        "accessibility_caption": null,
        "can_see_insights_as_brand": false,
        "caption_is_edited": false,
        "clips_music_attribution_info": {
            "artist_name": "nick.zei",
            "audio_id": "1709308899627078",
            "should_mute_audio": false,
            "should_mute_audio_reason": "",
            "song_name": "Original audio",
            "uses_original_audio": true
        },
        "coauthor_producers": [],
        "commenting_disabled_for_viewer": false,
        "comments_disabled": false,
        "dash_info": {
            "is_dash_eligible": false,
            "number_of_qualities": 0,
            "video_dash_manifest": null
        },
        "dimensions": {
            "height": 1920,
            "width": 1080
        },
        "display_resources": [
            {
                "config_height": 1137,
                "config_width": 640,
                "src": "https://scontent-yyz1-1.cdninstagram.com/v/t51.29350-15/476338734_958595246370754_8050552699180857847_n.jpg?stp=dst-jpg_e35_p640x640_sh0.08_tt6&_nc_ht=scontent-yyz1-1.cdninstagram.com&_nc_cat=110&_nc_oc=Q6cZ2AHFXss7tDhBpj-MYIrT8X3otgy0HMJJCuOgaJKy1QmtWGessfKcxLf9LxS7gxa5SK0&_nc_ohc=shq7_EntsMEQ7kNvgE8NiGd&_nc_gid=51ab0af671da491db4d687d896d2d1c3&edm=ANTKIIoBAAAA&ccb=7-5&oh=00_AYDxsZRbNJzDzTvaI9l4NLKycuj3VsgViIwG2th7u6RzLw&oe=67B53765&_nc_sid=d885a2"
            },
            {
                "config_height": 1333,
                "config_width": 750,
                "src": "https://scontent-yyz1-1.cdninstagram.com/v/t51.29350-15/476338734_958595246370754_8050552699180857847_n.jpg?stp=dst-jpg_e35_p750x750_sh0.08_tt6&_nc_ht=scontent-yyz1-1.cdninstagram.com&_nc_cat=110&_nc_oc=Q6cZ2AHFXss7tDhBpj-MYIrT8X3otgy0HMJJCuOgaJKy1QmtWGessfKcxLf9LxS7gxa5SK0&_nc_ohc=shq7_EntsMEQ7kNvgE8NiGd&_nc_gid=51ab0af671da491db4d687d896d2d1c3&edm=ANTKIIoBAAAA&ccb=7-5&oh=00_AYAtMfm6sqxD8pFge9w5qZP5qlyS33Ayy7Lgy0sCMpflXw&oe=67B53765&_nc_sid=d885a2"
            },
            {
                "config_height": 1920,
                "config_width": 1080,
                "src": "https://scontent-yyz1-1.cdninstagram.com/v/t51.29350-15/476338734_958595246370754_8050552699180857847_n.jpg?stp=dst-jpg_e15_fr_p1080x1080_tt6&_nc_ht=scontent-yyz1-1.cdninstagram.com&_nc_cat=110&_nc_oc=Q6cZ2AHFXss7tDhBpj-MYIrT8X3otgy0HMJJCuOgaJKy1QmtWGessfKcxLf9LxS7gxa5SK0&_nc_ohc=shq7_EntsMEQ7kNvgE8NiGd&_nc_gid=51ab0af671da491db4d687d896d2d1c3&edm=ANTKIIoBAAAA&ccb=7-5&oh=00_AYAS0PpIhqtVyzmO4G_puuBKHbfdKARazUl0jy2Efuy4Nw&oe=67B53765&_nc_sid=d885a2"
            }
        ],
        "display_url": "https://scontent-yyz1-1.cdninstagram.com/v/t51.29350-15/476338734_958595246370754_8050552699180857847_n.jpg?stp=dst-jpg_e15_fr_p1080x1080_tt6&_nc_ht=scontent-yyz1-1.cdninstagram.com&_nc_cat=110&_nc_oc=Q6cZ2AHFXss7tDhBpj-MYIrT8X3otgy0HMJJCuOgaJKy1QmtWGessfKcxLf9LxS7gxa5SK0&_nc_ohc=shq7_EntsMEQ7kNvgE8NiGd&_nc_gid=51ab0af671da491db4d687d896d2d1c3&edm=ANTKIIoBAAAA&ccb=7-5&oh=00_AYAS0PpIhqtVyzmO4G_puuBKHbfdKARazUl0jy2Efuy4Nw&oe=67B53765&_nc_sid=d885a2",
        "edge_media_preview_comment": {
            "count": 1023,
            "edges": [
                {
                    "node": {
                        "created_at": 1739517558,
                        "did_report_as_spam": false,
                        "edge_liked_by": {
                            "count": 0
                        },
                        "id": "18091891843535607",
                        "is_restricted_pending": false,
                        "owner": {
                            "id": "10381538086",
                            "is_verified": false,
                            "profile_pic_url": "https://scontent-yyz1-1.cdninstagram.com/v/t51.2885-19/66429183_474149370081175_2499721247454134272_n.jpg?stp=dst-jpg_s150x150_tt6&_nc_ht=scontent-yyz1-1.cdninstagram.com&_nc_cat=107&_nc_oc=Q6cZ2AHFXss7tDhBpj-MYIrT8X3otgy0HMJJCuOgaJKy1QmtWGessfKcxLf9LxS7gxa5SK0&_nc_ohc=d73vxEbetKEQ7kNvgH1bzTB&_nc_gid=51ab0af671da491db4d687d896d2d1c3&edm=ANTKIIoBAAAA&ccb=7-5&oh=00_AYCcj43KAjK8LbaQus5D15gsXgIJ_b60_L6jCoNoSYpz0Q&oe=67B54497&_nc_sid=d885a2",
                            "username": "samantics88"
                        },
                        "text": "This is exactly what I was taught it meant. The I AM presence within yourself to your divine self is what Jesus was talking about, not him literally.",
                        "viewer_has_liked": false
                    }
                }
            ]
        },
        "edge_media_preview_like": {
            "count": 9459,
            "edges": []
        },
        "edge_media_to_caption": {
            "edges": [
                {
                    "node": {
                        "created_at": "1738622164",
                        "id": "18076359679646566",
                        "text": "There is a lot I did not mention in this because I wanted to keep it under 3 minutes for time purposes. \n\nThere is so much more to this that is in my full esoteric Bible study. \n\nCheck that out on my page here @nick.zei and tap my academy in the usual spot you find these things. \ud83d\udd25\n\n#christconsciousness #christconciousness #christconsiousness #esotericknowledge #esotericchristianity #hiddenmeanings"
                    }
                }
            ]
        },
        "edge_media_to_hoisted_comment": {
            "edges": []
        },
        "edge_media_to_parent_comment": {
            "count": 1023,
            "edges": [
                {
                    "node": {
                        "created_at": 1739517558,
                        "did_report_as_spam": false,
                        "edge_liked_by": {
                            "count": 0
                        },
                        "edge_threaded_comments": {
                            "count": 0,
                            "edges": [],
                            "page_info": {
                                "end_cursor": null,
                                "has_next_page": false
                            }
                        },
                        "id": "18091891843535607",
                        "is_restricted_pending": false,
                        "owner": {
                            "id": "10381538086",
                            "is_verified": false,
                            "profile_pic_url": "https://scontent-yyz1-1.cdninstagram.com/v/t51.2885-19/66429183_474149370081175_2499721247454134272_n.jpg?stp=dst-jpg_s150x150_tt6&_nc_ht=scontent-yyz1-1.cdninstagram.com&_nc_cat=107&_nc_oc=Q6cZ2AHFXss7tDhBpj-MYIrT8X3otgy0HMJJCuOgaJKy1QmtWGessfKcxLf9LxS7gxa5SK0&_nc_ohc=d73vxEbetKEQ7kNvgH1bzTB&_nc_gid=51ab0af671da491db4d687d896d2d1c3&edm=ANTKIIoBAAAA&ccb=7-5&oh=00_AYCcj43KAjK8LbaQus5D15gsXgIJ_b60_L6jCoNoSYpz0Q&oe=67B54497&_nc_sid=d885a2",
                            "username": "samantics88"
                        },
                        "text": "This is exactly what I was taught it meant. The I AM presence within yourself to your divine self is what Jesus was talking about, not him literally.",
                        "viewer_has_liked": false
                    }
                },
                {
                    "node": {
                        "created_at": 1739501694,
                        "did_report_as_spam": false,
                        "edge_liked_by": {
                            "count": 0
                        },
                        "edge_threaded_comments": {
                            "count": 0,
                            "edges": [],
                            "page_info": {
                                "end_cursor": null,
                                "has_next_page": false
                            }
                        },
                        "id": "17898867618132690",
                        "is_restricted_pending": false,
                        "owner": {
                            "id": "54686329105",
                            "is_verified": false,
                            "profile_pic_url": "https://scontent-yyz1-1.cdninstagram.com/v/t51.2885-19/470265000_1317902582711042_3292490146071026939_n.jpg?stp=dst-jpg_s150x150_tt6&_nc_ht=scontent-yyz1-1.cdninstagram.com&_nc_cat=102&_nc_oc=Q6cZ2AHFXss7tDhBpj-MYIrT8X3otgy0HMJJCuOgaJKy1QmtWGessfKcxLf9LxS7gxa5SK0&_nc_ohc=_stnMaNoLqMQ7kNvgFjJ5zx&_nc_gid=51ab0af671da491db4d687d896d2d1c3&edm=ANTKIIoBAAAA&ccb=7-5&oh=00_AYAB6eHUs-VoejTkOW5LlAfFkXhFVWOYCvLQNN8mghM8QQ&oe=67B52BCA&_nc_sid=d885a2",
                            "username": "robynmhouse"
                        },
                        "text": "The mental gymnastics and twisting of words in this video is nauseating. If he heard a well-informed biblical scholar explain in great detail why his premise is faulty to begin with and how his entire hermeneutical approach is bias eisegesis, he would probably still not change his mind because this is not about linguistics or historical context, it's about denying Christ's claim to be the only way to the Father.",
                        "viewer_has_liked": false
                    }
                },
                {
                    "node": {
                        "created_at": 1739501376,
                        "did_report_as_spam": false,
                        "edge_liked_by": {
                            "count": 0
                        },
                        "edge_threaded_comments": {
                            "count": 0,
                            "edges": [],
                            "page_info": {
                                "end_cursor": null,
                                "has_next_page": false
                            }
                        },
                        "id": "18347571232180073",
                        "is_restricted_pending": false,
                        "owner": {
                            "id": "54686329105",
                            "is_verified": false,
                            "profile_pic_url": "https://scontent-yyz1-1.cdninstagram.com/v/t51.2885-19/470265000_1317902582711042_3292490146071026939_n.jpg?stp=dst-jpg_s150x150_tt6&_nc_ht=scontent-yyz1-1.cdninstagram.com&_nc_cat=102&_nc_oc=Q6cZ2AHFXss7tDhBpj-MYIrT8X3otgy0HMJJCuOgaJKy1QmtWGessfKcxLf9LxS7gxa5SK0&_nc_ohc=_stnMaNoLqMQ7kNvgFjJ5zx&_nc_gid=51ab0af671da491db4d687d896d2d1c3&edm=ANTKIIoBAAAA&ccb=7-5&oh=00_AYAB6eHUs-VoejTkOW5LlAfFkXhFVWOYCvLQNN8mghM8QQ&oe=67B52BCA&_nc_sid=d885a2",
                            "username": "robynmhouse"
                        },
                        "text": "@wesley_huff would have a field day with this video",
                        "viewer_has_liked": false
                    }
                },
                {
                    "node": {
                        "created_at": 1739499586,
                        "did_report_as_spam": false,
                        "edge_liked_by": {
                            "count": 0
                        },
                        "edge_threaded_comments": {
                            "count": 0,
                            "edges": [],
                            "page_info": {
                                "end_cursor": null,
                                "has_next_page": false
                            }
                        },
                        "id": "18032767997268483",
                        "is_restricted_pending": false,
                        "owner": {
                            "id": "179493309",
                            "is_verified": false,
                            "profile_pic_url": "https://scontent-yyz1-1.cdninstagram.com/v/t51.2885-19/472433675_1758950628012084_7991468478339695628_n.jpg?stp=dst-jpg_s150x150_tt6&_nc_ht=scontent-yyz1-1.cdninstagram.com&_nc_cat=100&_nc_oc=Q6cZ2AHFXss7tDhBpj-MYIrT8X3otgy0HMJJCuOgaJKy1QmtWGessfKcxLf9LxS7gxa5SK0&_nc_ohc=yLOZ97QYvlAQ7kNvgFQ1r3d&_nc_gid=51ab0af671da491db4d687d896d2d1c3&edm=ANTKIIoBAAAA&ccb=7-5&oh=00_AYCaDKLu-CWCsOhN0IJzqqRVVZrGshcJ539r0OdSo2V8-Q&oe=67B524EF&_nc_sid=d885a2",
                            "username": "raquellelizabethisgood"
                        },
                        "text": "\ud83d\ude4c\ud83d\udcaf",
                        "viewer_has_liked": false
                    }
                },
                {
                    "node": {
                        "created_at": 1739491000,
                        "did_report_as_spam": false,
                        "edge_liked_by": {
                            "count": 0
                        },
                        "edge_threaded_comments": {
                            "count": 0,
                            "edges": [],
                            "page_info": {
                                "end_cursor": null,
                                "has_next_page": false
                            }
                        },
                        "id": "18048375833247027",
                        "is_restricted_pending": false,
                        "owner": {
                            "id": "8746905592",
                            "is_verified": false,
                            "profile_pic_url": "https://scontent-yyz1-1.cdninstagram.com/v/t51.2885-19/474351013_906717158203300_9101099143855125176_n.jpg?stp=dst-jpg_s150x150_tt6&_nc_ht=scontent-yyz1-1.cdninstagram.com&_nc_cat=104&_nc_oc=Q6cZ2AHFXss7tDhBpj-MYIrT8X3otgy0HMJJCuOgaJKy1QmtWGessfKcxLf9LxS7gxa5SK0&_nc_ohc=-9nOuhasug4Q7kNvgEWKYpD&_nc_gid=51ab0af671da491db4d687d896d2d1c3&edm=ANTKIIoBAAAA&ccb=7-5&oh=00_AYAK38edopqr9isFWG32nIH7Iiwe-ExGrEoQkbyHfz8wGg&oe=67B531DD&_nc_sid=d885a2",
                            "username": "bossaimeeloo"
                        },
                        "text": "Yashua never went by Jesus. Aramaic had no letter J. Names do not change by accident",
                        "viewer_has_liked": false
                    }
                },
                {
                    "node": {
                        "created_at": 1739485359,
                        "did_report_as_spam": false,
                        "edge_liked_by": {
                            "count": 0
                        },
                        "edge_threaded_comments": {
                            "count": 0,
                            "edges": [],
                            "page_info": {
                                "end_cursor": null,
                                "has_next_page": false
                            }
                        },
                        "id": "18264222352273024",
                        "is_restricted_pending": false,
                        "owner": {
                            "id": "45959469129",
                            "is_verified": false,
                            "profile_pic_url": "https://scontent-yyz1-1.cdninstagram.com/v/t51.2885-19/453064052_1012946030236083_4830242121880402484_n.jpg?stp=dst-jpg_s150x150_tt6&_nc_ht=scontent-yyz1-1.cdninstagram.com&_nc_cat=103&_nc_oc=Q6cZ2AHFXss7tDhBpj-MYIrT8X3otgy0HMJJCuOgaJKy1QmtWGessfKcxLf9LxS7gxa5SK0&_nc_ohc=CtKU2LF2HTkQ7kNvgEx71u3&_nc_gid=51ab0af671da491db4d687d896d2d1c3&edm=ANTKIIoBAAAA&ccb=7-5&oh=00_AYBxlSebR4ErwRB8QsbKjLWD0T7twY3jnK0EKS1vXw6LxA&oe=67B54224&_nc_sid=d885a2",
                            "username": "nicgenn"
                        },
                        "text": "Remember friends, only the enemy wants to take our focus away from Jesus, if even for a moment \ud83d\ude22\ud83d\ude4f",
                        "viewer_has_liked": false
                    }
                },
                {
                    "node": {
                        "created_at": 1739480717,
                        "did_report_as_spam": false,
                        "edge_liked_by": {
                            "count": 0
                        },
                        "edge_threaded_comments": {
                            "count": 0,
                            "edges": [],
                            "page_info": {
                                "end_cursor": null,
                                "has_next_page": false
                            }
                        },
                        "id": "18015492140498395",
                        "is_restricted_pending": false,
                        "owner": {
                            "id": "50769051432",
                            "is_verified": false,
                            "profile_pic_url": "https://scontent-yyz1-1.cdninstagram.com/v/t51.2885-19/474650676_2017452125402043_5800138124622776431_n.jpg?stp=dst-jpg_s150x150_tt6&_nc_ht=scontent-yyz1-1.cdninstagram.com&_nc_cat=103&_nc_oc=Q6cZ2AHFXss7tDhBpj-MYIrT8X3otgy0HMJJCuOgaJKy1QmtWGessfKcxLf9LxS7gxa5SK0&_nc_ohc=ufs6uEVlA1wQ7kNvgGIp3Qh&_nc_gid=51ab0af671da491db4d687d896d2d1c3&edm=ANTKIIoBAAAA&ccb=7-5&oh=00_AYA1Q0Xv3qlulQYNR8dGs4LZ9m1GBQOw8VWBrA0VMQgYLg&oe=67B555F8&_nc_sid=d885a2",
                            "username": "dasnichten"
                        },
                        "text": "@inspiringphilosophy_ you got a doppelg\u00e4nger",
                        "viewer_has_liked": false
                    }
                },
                {
                    "node": {
                        "created_at": 1739480287,
                        "did_report_as_spam": false,
                        "edge_liked_by": {
                            "count": 0
                        },
                        "edge_threaded_comments": {
                            "count": 0,
                            "edges": [],
                            "page_info": {
                                "end_cursor": null,
                                "has_next_page": false
                            }
                        },
                        "id": "18060663709800093",
                        "is_restricted_pending": false,
                        "owner": {
                            "id": "62754912635",
                            "is_verified": false,
                            "profile_pic_url": "https://scontent-yyz1-1.cdninstagram.com/v/t51.2885-19/469176449_2203571286706907_1569417107535653887_n.jpg?stp=dst-jpg_s150x150_tt6&_nc_ht=scontent-yyz1-1.cdninstagram.com&_nc_cat=111&_nc_oc=Q6cZ2AHFXss7tDhBpj-MYIrT8X3otgy0HMJJCuOgaJKy1QmtWGessfKcxLf9LxS7gxa5SK0&_nc_ohc=npvisCMbpWMQ7kNvgFfQw_h&_nc_gid=51ab0af671da491db4d687d896d2d1c3&edm=ANTKIIoBAAAA&ccb=7-5&oh=00_AYDaM568Zv85i9lDCl-tPvqd_P0xgQJ0KtlsmUl5JRwD2w&oe=67B54128&_nc_sid=d885a2",
                            "username": "rv9nell"
                        },
                        "text": "",
                        "viewer_has_liked": false
                    }
                }
            ],
            "page_info": {
                "end_cursor": "{\"server_cursor\": \"QVFCdklvWEVPRjRvaGpyS0M4UHZreURyMktsQmg3b1hxYm5YVjB5WDJGVGR6WWtsTHVFNGF3SVJZSXF0R1NaS2t5MXRMWHV2UnJaNFpnd0RVV0dmM01SYg==\", \"is_server_cursor_inverse\": true}",
                "has_next_page": true
            }
        },
        "edge_media_to_sponsor_user": {
            "edges": []
        },
        "edge_media_to_tagged_user": {
            "edges": []
        },
        "edge_web_media_to_related_media": {
            "edges": []
        },
        "encoding_status": null,
        "fact_check_information": null,
        "fact_check_overall_rating": null,
        "gating_info": null,
        "has_audio": true,
        "has_ranked_comments": false,
        "id": "3560137510498180171",
        "is_ad": false,
        "is_affiliate": false,
        "is_paid_partnership": false,
        "is_published": true,
        "is_video": true,
        "like_and_view_counts_disabled": false,
        "location": null,
        "media_overlay_info": null,
        "media_preview": "ABgqqGRgcDAAprhGOR/LNCgZxjJ9KCwXIIwwPrmpbKQ/gjaF4HPJ/wD10U1Z1HXH6UVOpd0VjLtPA54INMdzKctyae0RHKnPHrik2MBk4H4jP6VZGq0IvLPofXp6UVL9ocghixyMcknuOf0opagVFJz1qTfzjH+fypgoHWqJJQuCST9PzoqMmilYq5//2Q==",
        "nft_asset_info": null,
        "owner": {
            "blocked_by_viewer": false,
            "edge_followed_by": {
                "count": 213417
            },
            "edge_owner_to_timeline_media": {
                "count": 623
            },
            "followed_by_viewer": false,
            "full_name": "Nick Zei",
            "has_blocked_viewer": false,
            "id": "30607240036",
            "is_embeds_disabled": false,
            "is_private": false,
            "is_unpublished": false,
            "is_verified": false,
            "pass_tiering_recommendation": true,
            "profile_pic_url": "https://scontent-yyz1-1.cdninstagram.com/v/t51.2885-19/460788607_450050284071535_7352870507851402617_n.jpg?stp=dst-jpg_s150x150_tt6&_nc_ht=scontent-yyz1-1.cdninstagram.com&_nc_cat=107&_nc_oc=Q6cZ2AHFXss7tDhBpj-MYIrT8X3otgy0HMJJCuOgaJKy1QmtWGessfKcxLf9LxS7gxa5SK0&_nc_ohc=6osVl_C2jRIQ7kNvgHJopeV&_nc_gid=51ab0af671da491db4d687d896d2d1c3&edm=ANTKIIoBAAAA&ccb=7-5&oh=00_AYBmnTgrswN1KPDTvkSB5hCFhewZ0JYIAsbp9GMl1f7cyw&oe=67B5239F&_nc_sid=d885a2",
            "requested_by_viewer": false,
            "restricted_by_viewer": null,
            "username": "nick.zei"
        },
        "pinned_for_users": [],
        "product_type": "clips",
        "sensitivity_friction_info": null,
        "sharing_friction_info": {
            "bloks_app_url": null,
            "should_have_sharing_friction": false
        },
        "shortcode": "DFoJjQQyZxL",
        "taken_at_timestamp": 1738622163,
        "thumbnail_src": "https://scontent-yyz1-1.cdninstagram.com/v/t51.29350-15/476338734_958595246370754_8050552699180857847_n.jpg?stp=c0.420.1080.1080a_dst-jpg_e35_s640x640_sh0.08_tt6&_nc_ht=scontent-yyz1-1.cdninstagram.com&_nc_cat=110&_nc_oc=Q6cZ2AHFXss7tDhBpj-MYIrT8X3otgy0HMJJCuOgaJKy1QmtWGessfKcxLf9LxS7gxa5SK0&_nc_ohc=shq7_EntsMEQ7kNvgE8NiGd&_nc_gid=51ab0af671da491db4d687d896d2d1c3&edm=ANTKIIoBAAAA&ccb=7-5&oh=00_AYAxL_QRHr7kCDqKmV6TeWhvjdqKJ4rfXnf2S8qdBdwu8w&oe=67B53765&_nc_sid=d885a2",
        "title": "",
        "tracking_token": "eyJ2ZXJzaW9uIjo1LCJwYXlsb2FkIjp7ImlzX2FuYWx5dGljc190cmFja2VkIjp0cnVlLCJ1dWlkIjoiNTFhYjBhZjY3MWRhNDkxZGI0ZDY4N2Q4OTZkMmQxYzMzNTYwMTM3NTEwNDk4MTgwMTcxIn0sInNpZ25hdHVyZSI6IiJ9",
        "upcoming_event": null,
        "video_duration": 178.373,
        "video_play_count": 146935,
        "video_url": "https://scontent-yyz1-1.cdninstagram.com/o1/v/t16/f2/m86/AQOTdrHXhjDP2za6CQuipxjkBGs3s000Cmax1nhfqDGonI1l3zRYpQiFCP65Ij9z4xguO1yluQ8G4deoYdsP1igkpM-MYOBIAg5soPo.mp4?stp=dst-mp4&efg=eyJxZV9ncm91cHMiOiJbXCJpZ193ZWJfZGVsaXZlcnlfdnRzX290ZlwiXSIsInZlbmNvZGVfdGFnIjoidnRzX3ZvZF91cmxnZW4uY2xpcHMuYzIuNzIwLmJhc2VsaW5lIn0&_nc_cat=101&vs=1200981365361330_114887872&_nc_vs=HBksFQIYUmlnX3hwdl9yZWVsc19wZXJtYW5lbnRfc3JfcHJvZC83NDQ3NTlBOUI3QjFGQUMxMDAyRjdDRDQzNjkwQjZBOF92aWRlb19kYXNoaW5pdC5tcDQVAALIAQAVAhg6cGFzc3Rocm91Z2hfZXZlcnN0b3JlL0dKeHpYUnlRYlkzVzZ5WUNBQS1ZT0Jqc2U5dE1icV9FQUFBRhUCAsgBACgAGAAbABUAACbotJnbn7efQBUCKAJDMywXQGZLtkWhysEYEmRhc2hfYmFzZWxpbmVfMV92MREAdf4HAA%3D%3D&ccb=9-4&oh=00_AYAyijYJLaIjdfam2IYXTN5OqVo4Cdk6wtKYVL0JCwdKnQ&oe=67B1312E&_nc_sid=d885a2",
        "video_view_count": 78061,
        "viewer_can_reshare": true,
        "viewer_has_liked": false,
        "viewer_has_saved": false,
        "viewer_has_saved_to_collection": false,
        "viewer_in_photo_of_you": false
    }
}